bsdauth/__init__.py
bsdauth/bsdauth.py
py_bsdauth-1.1.2.dist-info/LICENSE
py_bsdauth-1.1.2.dist-info/METADATA
py_bsdauth-1.1.2.dist-info/WHEEL
py_bsdauth-1.1.2.dist-info/top_level.txt
py_bsdauth-1.1.2.dist-info/RECORD
