Metadata-Version: 2.1
Name: py-bsdauth
Version: 1.1.2
Summary: Python interface to OpenBSD's BSD Auth.
Home-page: https://github.com/rbaylon/py-bsdauth
Author: Ricardo Baylon
Author-email: rbaylon@outlook.com
License: ISC
Platform: OpenBSD
Classifier: License :: OSI Approved :: ISC License (ISCL)
Classifier: Programming Language :: Python :: 3
License-File: LICENSE
